olib_ai/__init__.py
olib_ai-0.1.0.dist-info/licenses/LICENSE
olib_ai-0.1.0.dist-info/METADATA
olib_ai-0.1.0.dist-info/WHEEL
olib_ai-0.1.0.dist-info/top_level.txt
olib_ai-0.1.0.dist-info/RECORD
