Metadata-Version: 2.4
Name: olib-ai
Version: 0.1.0
Summary: Olib AI - Python SDK (Coming Soon)
Home-page: https://github.com/Olib-AI/olib-ai-python
Author: Olib AI
Author-email: akram@olib.ai
Classifier: Programming Language :: Python :: 3
Classifier: License :: OSI Approved :: MIT License
Classifier: Operating System :: OS Independent
Classifier: Development Status :: 2 - Pre-Alpha
Requires-Python: >=3.12
License-File: LICENSE
Dynamic: author
Dynamic: author-email
Dynamic: classifier
Dynamic: description
Dynamic: description-content-type
Dynamic: home-page
Dynamic: license-file
Dynamic: requires-python
Dynamic: summary
